cuefix/__init__.py
cuefix/cli.py
cuefix/cuefix.py
cuefix/version.py
cuefix-0.1.3.dist-info/LICENSE
cuefix-0.1.3.dist-info/METADATA
cuefix-0.1.3.dist-info/WHEEL
cuefix-0.1.3.dist-info/entry_points.txt
cuefix-0.1.3.dist-info/top_level.txt
cuefix-0.1.3.dist-info/RECORD
