Metadata-Version: 2.1
Name: cuefix
Version: 0.1.3
Summary: A simple tool to fix problematic CUE files.
Home-page: https://github.com/yinyanghu/cuefix
Author-email: lijianxp2005@gmail.com
License: UNKNOWN
Platform: UNKNOWN
Classifier: Programming Language :: Python :: 3 :: Only
Classifier: Programming Language :: Python :: 3.6
Classifier: Programming Language :: Python :: 3.7
Classifier: Programming Language :: Python :: 3.8
Classifier: Programming Language :: Python :: 3.9
Classifier: License :: OSI Approved :: GNU General Public License v3 (GPLv3)
Classifier: Operating System :: OS Independent
Requires-Python: >=3.6
Requires-Dist: chardet (>=3.0.4)
